cudra/__init__.py
cudra/cudra.py
cudra-0.0.3.dist-info/LICENSE
cudra-0.0.3.dist-info/METADATA
cudra-0.0.3.dist-info/WHEEL
cudra-0.0.3.dist-info/top_level.txt
cudra-0.0.3.dist-info/RECORD
